<?xml version="1.0" encoding="UTF-8"?>
<!DOCTYPE mapper PUBLIC "-//mybatis.org//DTD Mapper 3.0//EN" "http://mybatis.org/dtd/mybatis-3-mapper.dtd">
<mapper namespace="com.ysu.graduationproject.dao.ResultMapper">
  <resultMap id="BaseResultMap" type="com.ysu.graduationproject.po.Result">
    <!--
      WARNING - @mbg.generated
      This element is automatically generated by MyBatis Generator, do not modify.
      This element was generated on Tue Apr 07 13:19:28 CST 2020.
    -->
    <id column="tableId" jdbcType="VARCHAR" property="tableid" />
    <result column="patientId" jdbcType="VARCHAR" property="patientid" />
    <result column="type" jdbcType="VARCHAR" property="type" />
    <result column="content" jdbcType="VARCHAR" property="content" />
    <result column="createTime" jdbcType="DATE" property="createtime" />
    <result column="delFlag" jdbcType="VARCHAR" property="delflag" />
  </resultMap>
  <sql id="Base_Column_List">
    <!--
      WARNING - @mbg.generated
      This element is automatically generated by MyBatis Generator, do not modify.
      This element was generated on Tue Apr 07 13:19:28 CST 2020.
    -->
    tableId, patientId, type, content, createTime, delFlag
  </sql>
  <select id="selectByPrimaryKey" parameterType="java.lang.String" resultMap="BaseResultMap">
    <!--
      WARNING - @mbg.generated
      This element is automatically generated by MyBatis Generator, do not modify.
      This element was generated on Tue Apr 07 13:19:28 CST 2020.
    -->
    select 
    <include refid="Base_Column_List" />
    from result
    where patientId = #{patientId,jdbcType=VARCHAR}
  </select>

  <select id="selectResultAll" parameterType="java.lang.String" resultMap="BaseResultMap">
    <!--
      WARNING - @mbg.generated
      This element is automatically generated by MyBatis Generator, do not modify.
      This element was generated on Tue Apr 07 13:19:28 CST 2020.
    -->
    select
    <include refid="Base_Column_List" />
    from result
    where tableId = #{tableid,jdbcType=VARCHAR}
    order by createTime desc
  </select>

  <delete id="deleteByPrimaryKey" parameterType="java.lang.String">
    <!--
      WARNING - @mbg.generated
      This element is automatically generated by MyBatis Generator, do not modify.
      This element was generated on Tue Apr 07 13:19:28 CST 2020.
    -->
    delete from result
    where tableId = #{tableid,jdbcType=VARCHAR}
  </delete>
  <insert id="insert" parameterType="com.ysu.graduationproject.po.Result">
    <!--
      WARNING - @mbg.generated
      This element is automatically generated by MyBatis Generator, do not modify.
      This element was generated on Tue Apr 07 13:19:28 CST 2020.
    -->
    insert into result (tableId, patientId, type, 
      content, createTime, delFlag
      )
    values (#{tableid,jdbcType=VARCHAR}, #{patientid,jdbcType=VARCHAR}, #{type,jdbcType=VARCHAR}, 
      #{content,jdbcType=VARCHAR},now(), #{delflag,jdbcType=VARCHAR}
      )
  </insert>
  <insert id="insertSelective" parameterType="com.ysu.graduationproject.po.Result">
    <!--
      WARNING - @mbg.generated
      This element is automatically generated by MyBatis Generator, do not modify.
      This element was generated on Tue Apr 07 13:19:28 CST 2020.
    -->
    insert into result
    <trim prefix="(" suffix=")" suffixOverrides=",">
      <if test="tableid != null">
        tableId,
      </if>
      <if test="patientid != null">
        patientId,
      </if>
      <if test="type != null">
        type,
      </if>
      <if test="content != null">
        content,
      </if>
      <if test="createtime != null">
        createTime,
      </if>
      <if test="delflag != null">
        delFlag,
      </if>
    </trim>
    <trim prefix="values (" suffix=")" suffixOverrides=",">
      <if test="tableid != null">
        #{tableid,jdbcType=VARCHAR},
      </if>
      <if test="patientid != null">
        #{patientid,jdbcType=VARCHAR},
      </if>
      <if test="type != null">
        #{type,jdbcType=VARCHAR},
      </if>
      <if test="content != null">
        #{content,jdbcType=VARCHAR},
      </if>
      now(),
      <if test="delflag != null">
        #{delflag,jdbcType=VARCHAR},
      </if>
    </trim>
  </insert>
  <update id="updateByPrimaryKeySelective" parameterType="com.ysu.graduationproject.po.Result">
    <!--
      WARNING - @mbg.generated
      This element is automatically generated by MyBatis Generator, do not modify.
      This element was generated on Tue Apr 07 13:19:28 CST 2020.
    -->
    update result
    <set>
      <if test="patientid != null">
        patientId = #{patientid,jdbcType=VARCHAR},
      </if>
      <if test="type != null">
        type = #{type,jdbcType=VARCHAR},
      </if>
      <if test="content != null">
        content = #{content,jdbcType=VARCHAR},
      </if>
      <if test="delflag != null">
        delFlag = #{delflag,jdbcType=VARCHAR},
      </if>
    </set>
    where tableId = #{tableid,jdbcType=VARCHAR}
  </update>
  <update id="updateByPrimaryKey" parameterType="com.ysu.graduationproject.po.Result">
    <!--
      WARNING - @mbg.generated
      This element is automatically generated by MyBatis Generator, do not modify.
      This element was generated on Tue Apr 07 13:19:28 CST 2020.
    -->
    select d.tableId
    from patient p join patientcase c
    on p.tableId = c.patientId
    JOIN details d
    on c.tableId = d.caseId
    WHERE p.tableId = #{tableid,jdbcType=VARCHAR}
  </update>
</mapper>